{
  "info": {
    "_postman_id": "8c6b3e94-1a3b-4f9e-bc43-26f571b0aa44",
    "name": "CRM CallCenter - Semana 1 & 2",
    "description": "Colección de endpoints de API para los módulos de Autenticación, Leads, Pre-Venta, Órdenes y Catálogos de la solución CRM CallCenter.",
    "schema": "https://schema.getpostman.com/json/collection/v2.1.0/collection.json"
  },
  "item": [
    {
      "name": "Autenticación",
      "item": [
        {
          "name": "Login",
          "request": {
            "method": "POST",
            "header": [
              {
                "key": "Content-Type",
                "value": "application/json"
              }
            ],
            "body": {
              "mode": "raw",
              "raw": "{\n  \"username\": \"test.asesor\",\n  \"password\": \"password123\"\n}"
            },
            "url": {
              "raw": "{{base_url}}/api/auth/login",
              "host": [
                "{{base_url}}"
              ],
              "path": [
                "api",
                "auth",
                "login"
              ]
            }
          },
          "response": []
        },
        {
          "name": "Obtener Datos de Usuario (/me)",
          "request": {
            "method": "GET",
            "header": [
              {
                "key": "Authorization",
                "value": "Bearer {{jwt_token}}"
              }
            ],
            "url": {
              "raw": "{{base_url}}/api/auth/me",
              "host": [
                "{{base_url}}"
              ],
              "path": [
                "api",
                "auth",
                "me"
              ]
            }
          },
          "response": []
        },
        {
          "name": "Refrescar Token",
          "request": {
            "method": "POST",
            "header": [
              {
                "key": "Content-Type",
                "value": "application/json"
              }
            ],
            "body": {
              "mode": "raw",
              "raw": "{\n  \"accessToken\": \"{{jwt_token}}\",\n  \"refreshToken\": \"{{refresh_token}}\"\n}"
            },
            "url": {
              "raw": "{{base_url}}/api/auth/refresh-token",
              "host": [
                "{{base_url}}"
              ],
              "path": [
                "api",
                "auth",
                "refresh-token"
              ]
            }
          },
          "response": []
        },
        {
          "name": "Logout (Revocar Token)",
          "request": {
            "method": "POST",
            "header": [
              {
                "key": "Content-Type",
                "value": "application/json"
              }
            ],
            "body": {
              "mode": "raw",
              "raw": "{\n  \"token\": \"{{refresh_token}}\"\n}"
            },
            "url": {
              "raw": "{{base_url}}/api/auth/logout",
              "host": [
                "{{base_url}}"
              ],
              "path": [
                "api",
                "auth",
                "logout"
              ]
            }
          },
          "response": []
        }
      ]
    },
    {
      "name": "Leads",
      "item": [
        {
          "name": "Obtener Leads (Paginado)",
          "request": {
            "method": "GET",
            "header": [
              {
                "key": "Authorization",
                "value": "Bearer {{jwt_token}}"
              }
            ],
            "url": {
              "raw": "{{base_url}}/api/leads?page=1&pageSize=20&campaignId=1",
              "host": [
                "{{base_url}}"
              ],
              "path": [
                "api",
                "leads"
              ],
              "query": [
                {
                  "key": "page",
                  "value": "1"
                },
                {
                  "key": "pageSize",
                  "value": "20"
                },
                {
                  "key": "campaignId",
                  "value": "1"
                },
                {
                  "key": "search",
                  "value": "juan",
                  "disabled": true
                }
              ]
            }
          },
          "response": []
        },
        {
          "name": "Crear Lead",
          "request": {
            "method": "POST",
            "header": [
              {
                "key": "Content-Type",
                "value": "application/json"
              },
              {
                "key": "Authorization",
                "value": "Bearer {{jwt_token}}"
              }
            ],
            "body": {
              "mode": "raw",
              "raw": "{\n  \"firstName\": \"Juan\",\n  \"lastName\": \"Pérez\",\n  \"email\": \"juan.perez@email.com\",\n  \"phoneNumber\": \"+51999888777\",\n  \"campaignId\": 1\n}"
            },
            "url": {
              "raw": "{{base_url}}/api/leads",
              "host": [
                "{{base_url}}"
              ],
              "path": [
                "api",
                "leads"
              ]
            }
          },
          "response": []
        },
        {
          "name": "Obtener Lead por ID",
          "request": {
            "method": "GET",
            "header": [
              {
                "key": "Authorization",
                "value": "Bearer {{jwt_token}}"
              }
            ],
            "url": {
              "raw": "{{base_url}}/api/leads/1",
              "host": [
                "{{base_url}}"
              ],
              "path": [
                "api",
                "leads",
                "1"
              ]
            }
          },
          "response": []
        }
      ]
    },
    {
      "name": "Pre-Venta",
      "item": [
        {
          "name": "Registrar Pre-Venta",
          "request": {
            "method": "POST",
            "header": [
              {
                "key": "Content-Type",
                "value": "application/json"
              },
              {
                "key": "Authorization",
                "value": "Bearer {{jwt_token}}"
              }
            ],
            "body": {
              "mode": "raw",
              "raw": "{\n  \"assignedUserId\": 10,\n  \"notes\": \"Asesor contactó cliente, interesado en plan Premium.\",\n  \"scheduledContactDate\": \"2026-07-08T14:00:00Z\"\n}"
            },
            "url": {
              "raw": "{{base_url}}/api/leads/1/presale",
              "host": [
                "{{base_url}}"
              ],
              "path": [
                "api",
                "leads",
                "1",
                "presale"
              ]
            }
          },
          "response": []
        },
        {
          "name": "Obtener Historial de Pre-Ventas",
          "request": {
            "method": "GET",
            "header": [
              {
                "key": "Authorization",
                "value": "Bearer {{jwt_token}}"
              }
            ],
            "url": {
              "raw": "{{base_url}}/api/leads/1/presale",
              "host": [
                "{{base_url}}"
              ],
              "path": [
                "api",
                "leads",
                "1",
                "presale"
              ]
            }
          },
          "response": []
        }
      ]
    },
    {
      "name": "Órdenes de Venta",
      "item": [
        {
          "name": "Crear Orden de Venta",
          "request": {
            "method": "POST",
            "header": [
              {
                "key": "Content-Type",
                "value": "application/json"
              },
              {
                "key": "Authorization",
                "value": "Bearer {{jwt_token}}"
              }
            ],
            "body": {
              "mode": "raw",
              "raw": "{\n  \"leadId\": 1,\n  \"products\": [\n    {\n      \"productId\": 3,\n      \"quantity\": 2\n    }\n  ],\n  \"notes\": \"Entrega urgente confirmada por el cliente.\"\n}"
            },
            "url": {
              "raw": "{{base_url}}/api/orders",
              "host": [
                "{{base_url}}"
              ],
              "path": [
                "api",
                "orders"
              ]
            }
          },
          "response": []
        },
        {
          "name": "Obtener Orden por ID",
          "request": {
            "method": "GET",
            "header": [
              {
                "key": "Authorization",
                "value": "Bearer {{jwt_token}}"
              }
            ],
            "url": {
              "raw": "{{base_url}}/api/orders/101",
              "host": [
                "{{base_url}}"
              ],
              "path": [
                "api",
                "orders",
                "101"
              ]
            }
          },
          "response": []
        },
        {
          "name": "Actualizar Estado de Orden",
          "request": {
            "method": "PUT",
            "header": [
              {
                "key": "Content-Type",
                "value": "application/json"
              },
              {
                "key": "Authorization",
                "value": "Bearer {{jwt_token}}"
              }
            ],
            "body": {
              "mode": "raw",
              "raw": "{\n  \"statusId\": 2,\n  \"substatusId\": 4,\n  \"comments\": \"Pago verificado por tesorería.\"\n}"
            },
            "url": {
              "raw": "{{base_url}}/api/orders/101/status",
              "host": [
                "{{base_url}}"
              ],
              "path": [
                "api",
                "orders",
                "101",
                "status"
              ]
            }
          },
          "response": []
        }
      ]
    },
    {
      "name": "Catálogos",
      "item": [
        {
          "name": "Listar Estados de Orden",
          "request": {
            "method": "GET",
            "header": [
              {
                "key": "Authorization",
                "value": "Bearer {{jwt_token}}"
              }
            ],
            "url": {
              "raw": "{{base_url}}/api/catalogs/statuses",
              "host": [
                "{{base_url}}"
              ],
              "path": [
                "api",
                "catalogs",
                "statuses"
              ]
            }
          },
          "response": []
        },
        {
          "name": "Listar Subestados por Estado",
          "request": {
            "method": "GET",
            "header": [
              {
                "key": "Authorization",
                "value": "Bearer {{jwt_token}}"
              }
            ],
            "url": {
              "raw": "{{base_url}}/api/catalogs/statuses/2/substatuses",
              "host": [
                "{{base_url}}"
              ],
              "path": [
                "api",
                "catalogs",
                "statuses",
                "2",
                "substatuses"
              ]
            }
          },
          "response": []
        },
        {
          "name": "Listar Productos por Campaña",
          "request": {
            "method": "GET",
            "header": [
              {
                "key": "Authorization",
                "value": "Bearer {{jwt_token}}"
              }
            ],
            "url": {
              "raw": "{{base_url}}/api/catalogs/campaigns/1/products",
              "host": [
                "{{base_url}}"
              ],
              "path": [
                "api",
                "catalogs",
                "campaigns",
                "1",
                "products"
              ]
            }
          },
          "response": []
        },
        {
          "name": "Listar Monedas",
          "request": {
            "method": "GET",
            "header": [
              {
                "key": "Authorization",
                "value": "Bearer {{jwt_token}}"
              }
            ],
            "url": {
              "raw": "{{base_url}}/api/catalogs/currencies",
              "host": [
                "{{base_url}}"
              ],
              "path": [
                "api",
                "catalogs",
                "currencies"
              ]
            }
          },
          "response": []
        }
      ]
    }
  ],
  "event": [
    {
      "listen": "prerequest",
      "script": {
        "type": "text/javascript",
        "exec": [
          ""
        ]
      }
    },
    {
      "listen": "test",
      "script": {
        "type": "text/javascript",
        "exec": [
          ""
        ]
      }
    }
  ],
  "variable": [
    {
      "key": "base_url",
      "value": "http://localhost:5068",
      "type": "string"
    },
    {
      "key": "jwt_token",
      "value": "reemplazar_con_el_token_recibido_en_login",
      "type": "string"
    },
    {
      "key": "refresh_token",
      "value": "reemplazar_con_el_refresh_token_recibido_en_login",
      "type": "string"
    }
  ]
}
